app.py
keepregister-0.1.0.dist-info/LICENSE
keepregister-0.1.0.dist-info/METADATA
keepregister-0.1.0.dist-info/WHEEL
keepregister-0.1.0.dist-info/entry_points.txt
keepregister-0.1.0.dist-info/top_level.txt
keepregister-0.1.0.dist-info/RECORD
