Metadata-Version: 2.1
Name: keepregister
Version: 0.1.0
Summary: This terminal app register a text with date and hour for you to keep track of your done work.
Home-page: https://github.com/hasher-hasher/keepregister
Author: Renan Rocha (hasher-hasher)
Author-email: renanoar04@gmail.com
License: UNKNOWN
Platform: UNKNOWN
Requires-Dist: Click
